xontrib/cmd_done.py
xontrib_cmd_durations-0.3.2.dist-info/WHEEL
xontrib_cmd_durations-0.3.2.dist-info/METADATA
xontrib_cmd_durations-0.3.2.dist-info/licenses/LICENSE
xontrib_cmd_durations-0.3.2.dist-info/RECORD
