Metadata-Version: 2.1
Name: xontrib-cmd-durations
Version: 0.3.2
Summary: Send notification once long running command is finished. Add duration PROMP_FIELD.
License: MIT
Keywords: xontrib,xonsh
Author-email: Noortheen Raja J <jnoortheen@gmail.com>
Requires-Python: >=3.7
Classifier: Intended Audience :: Developers
Classifier: License :: OSI Approved :: MIT License
Classifier: Natural Language :: English
Classifier: Operating System :: OS Independent
Classifier: Programming Language :: Python
Classifier: Programming Language :: Python :: 3
Classifier: Topic :: Software Development
Classifier: Topic :: System :: Shells
Classifier: Topic :: System :: System Shells
Classifier: Topic :: Terminals
Classifier: Topic :: Utilities
Requires-Dist: notify-py>=0.3.3; python_version >= "3.6" and python_version < "4.0"
Requires-Dist: xonsh>=0.10
Provides-Extra: dev
Requires-Dist: pytest; extra == "dev"
Requires-Dist: black; extra == "dev"
Project-URL: Code, https://github.com/jnoortheen/xontrib-cmd-durations
Project-URL: Documentation, https://github.com/jnoortheen/xontrib-cmd-durations/blob/master/README.md
Project-URL: Issue tracker, https://github.com/jnoortheen/xontrib-cmd-durations/issues
Project-URL: repository, https://github.com/jnoortheen/xontrib-cmd-durations
